lib_typ_parse/__api__.py
lib_typ_parse/__init__.py
lib_typ_parse/typon_client.py
lib_typ_parse/helper/__init__.py
lib_typ_parse/helper/eval_helper.py
lib_typ_parse/helper/eval_service.py
lib_typ_parse/helper/type_resolver.py
lib_typ_parse/parse/__init__.py
lib_typ_parse/parse/parse_L0_skeleton.py
lib_typ_parse/parse/parse_skeleton.py
lib_typ_parse/parse/parser.py
lib_typ_parse/utils/__init__.py
lib_typ_parse/utils/constants.py
lib_typ_parse/utils/exceptions.py
lib_typ_parse/utils/fmt_utils.py
lib_typ_parse/utils/parsing_utils.py
lib_typ_parse/utils/transform_data.py
typon_client-0.0.2.dist-info/METADATA
typon_client-0.0.2.dist-info/WHEEL
typon_client-0.0.2.dist-info/top_level.txt
typon_client-0.0.2.dist-info/RECORD
