Metadata-Version: 2.1
Name: typon-client
Version: 0.0.2
Home-page: http://pypi.python.org/pypi/typon_client/0.0.2
Author: hypothesisbase
Author-email: support@hypothesisbase.com
License: MIT
Requires-Dist: requests
